rf_event_listener/__init__.py
rf_event_listener/api.py
rf_event_listener/events.py
rf_event_listener/listener.py
rf_event_listener-0.0.5.dist-info/LICENSE
rf_event_listener-0.0.5.dist-info/METADATA
rf_event_listener-0.0.5.dist-info/WHEEL
rf_event_listener-0.0.5.dist-info/top_level.txt
rf_event_listener-0.0.5.dist-info/RECORD
