Metadata-Version: 2.1
Name: rf-event-listener
Version: 0.0.5
Summary: RedForester Event Listener
Home-page: https://github.com/RedForester/python_rf_event_listener
Author: Red Forester
Author-email: tech@redforester.com
License: MIT
Platform: UNKNOWN
Classifier: Programming Language :: Python :: 3
Classifier: Development Status :: 3 - Alpha
Classifier: License :: OSI Approved :: MIT License
Requires-Python: >=3.6
Requires-Dist: pydantic (~=1.5)
Requires-Dist: yarl (~=1.4)
Requires-Dist: aiohttp (~=3.6)
Provides-Extra: dev
Requires-Dist: pytest (~=5.4) ; extra == 'dev'
Requires-Dist: pytest-asyncio (~=0.12) ; extra == 'dev'
Requires-Dist: flake8 (~=3.8) ; extra == 'dev'
